[
    {
        "name": "최수호",
        "rank": "병장",
        "number": "2170012345",
        "working": "Off",
        "location": "생활관",
        "heartrate": 108
    },

    {
        "name": "윤지성",
        "rank": "병장",
        "number": "2170023456",
        "working": "On",
        "location": "AAOC",
        "heartrate": 82
    },
    {
        "name": "박원",
        "rank": "일병",
        "number": "2270007066",
        "working": "Off",
        "location": "생활관",
        "heartrate": 147
    }
]